aiomonitor/__init__.py
aiomonitor/cli.py
aiomonitor/console.py
aiomonitor/context.py
aiomonitor/exceptions.py
aiomonitor/monitor.py
aiomonitor/task.py
aiomonitor/telnet.py
aiomonitor/types.py
aiomonitor/utils.py
aiomonitor/termui/__init__.py
aiomonitor/termui/commands.py
aiomonitor/termui/completion.py
aiomonitor/webui/__init__.py
aiomonitor/webui/app.py
aiomonitor/webui/utils.py
aiomonitor/webui/static/alpine.js
aiomonitor/webui/static/client-side-templates.js
aiomonitor/webui/static/htmx.js
aiomonitor/webui/static/loader.svg
aiomonitor/webui/static/mustache.js
aiomonitor/webui/static/tailwind.js
aiomonitor/webui/templates/about.html
aiomonitor/webui/templates/index.html
aiomonitor/webui/templates/layout.html
aiomonitor/webui/templates/trace.html
aiomonitor-0.7.1.dist-info/LICENSE
aiomonitor-0.7.1.dist-info/METADATA
aiomonitor-0.7.1.dist-info/WHEEL
aiomonitor-0.7.1.dist-info/top_level.txt
aiomonitor-0.7.1.dist-info/RECORD
