Metadata-Version: 2.1
Name: aiomonitor
Version: 0.7.1
Summary: Adds monitor and Python REPL capabilities for asyncio applications
Download-URL: https://pypi.org/project/aiomonitor
Author: Nikolay Novik
Author-email: nickolainovik@gmail.com
Maintainer: Joongi Kim
Maintainer-email: me@daybreaker.info
License: Apache-2.0
Project-URL: Homepage, https://github.com/aio-libs/aiomonitor
Project-URL: Documentation, https://aiomonitor.readthedocs.io
Project-URL: Repository, https://github.com/aio-libs/aiomonitor
Project-URL: Issues, https://github.com/aio-libs/aiomonitor/issues
Project-URL: Changelog, https://github.com/aio-libs/aiomonitor/blob/main/CHANGES.rst
Project-URL: Chat, https://matrix.to/#/!aio-libs:matrix.org
Keywords: asyncio,aiohttp,monitor,debugging,utility,devtool
Platform: POSIX
Classifier: License :: OSI Approved :: Apache Software License
Classifier: Intended Audience :: Developers
Classifier: Programming Language :: Python :: 3
Classifier: Programming Language :: Python :: 3.9
Classifier: Programming Language :: Python :: 3.10
Classifier: Programming Language :: Python :: 3.11
Classifier: Programming Language :: Python :: 3.12
Classifier: Programming Language :: Python :: 3.13
Classifier: Operating System :: POSIX
Classifier: Development Status :: 3 - Alpha
Classifier: Framework :: AsyncIO
Requires-Python: >=3.8
License-File: LICENSE
Requires-Dist: attrs>=20
Requires-Dist: aiohttp>=3.8.5
Requires-Dist: click>=8.0
Requires-Dist: janus>=1.0
Requires-Dist: jinja2>=3.1.2
Requires-Dist: backports.strenum>=1.2.4; python_version < "3.11"
Requires-Dist: terminaltables
Requires-Dist: trafaret>=2.1.1
Requires-Dist: typing-extensions>=4.1
Requires-Dist: prompt_toolkit>=3.0
Requires-Dist: aioconsole>=0.7.0
Requires-Dist: telnetlib3>=2.0.4
